LICENSE.txt
MANIFEST.in
README.rst
setup.py
nosepride/__init__.py
nosepride/nosepride.py
nosepride/plugins.py
nosepride/reports.py
nosepride/streams.py
nosepride.egg-info/PKG-INFO
nosepride.egg-info/SOURCES.txt
nosepride.egg-info/dependency_links.txt
nosepride.egg-info/entry_points.txt
nosepride.egg-info/requires.txt
nosepride.egg-info/top_level.txt
nosepride/formatters/__init__.py
nosepride/formatters/base.py
nosepride/formatters/fabulous.py
nosepride/formatters/plain.py
nosepride/utils/__init__.py
nosepride/utils/lazy.py
nosepride/utils/shims.py
nosepride/utils/traceback.py