Metadata-Version: 1.1
Name: nosepride
Version: 0.1.7
Summary: Fabulous colors for nosetests
Home-page: https://github.com/hugobast/nosepride.git
Author: Hugo Bastien
Author-email: hugobast@gmail.com
License: MIT License
Platform: UNKNOWN
Classifier: Development Status :: 4 - Beta
Classifier: Topic :: Software Development :: Testing
Classifier: Environment :: Plugins
Classifier: Programming Language :: Python :: 2.7
Classifier: Programming Language :: Python :: 3.3
